[
  {
    "_id": "12033fa4-6b5a-49e0-8755-1dbae2804bb3",
    "version": 78,
    "type": "saml20_idp",
    "data": {
      "entityid": "urn:thki:sid:idp2",
      "state": "prodaccepted",
      "notes": null,
      "metaDataFields": {
        "name:nl": "thkidp NL",
        "logo:0:url": "https://static.surfconext.nl/media/idp/avat_st.jpg",
        "name:en": "thkidp EN",
        "OrganizationName:en": "Bolliger <strong> Mabillard</strong>",
        "coin:institution_brin_schac_home": "aap.nl",
        "shibmd:scope:0:allowed": "aap.nl",
        "shibmd:scope:1:allowed": "noot.je",
        "shibmd:scope:2:allowed": "sub1.aap.nl",
        "shibmd:scope:3:allowed": "sub2.aap.nl",
        "shibmd:scope:4:allowed": "sub3.aap.nl",
        "shibmd:scope:5:allowed": "example.nl",
        "shibmd:scope:6:allowed": "sub5.aap.nl",
        "shibmd:scope:7:allowed": "sub6.aap.nl",
        "shibmd:scope:8:allowed": "sub7.aap.nl",
        "shibmd:scope:9:allowed": "example.com",
        "coin:institution_brin": "ST42",
        "coin:institution_guid": "8017e83f-bca7-e911-90f2-0050569571ea"
      }
    }
  },
  {
    "_id": "51585505-59ff-4b9b-b4a5-8e352d4a068f",
    "version": 44,
    "type": "saml20_idp",
    "data": {
      "entityid": "http://adfs3host.proxy.rocmn.nl/adfs/services/trust",
      "state": "prodaccepted",
      "metaDataFields": {
        "name:en": "ROC Midden Nederland",
        "OrganizationName:nl": "ROC Midden Nederland NL",
        "OrganizationName:en": "ROC Midden Nederland EN",
        "coin:institution_brin_schac_home": "rocmn.nl",
        "shibmd:scope:0:allowed": "rocmn.nl",
        "logo:0:url": "https://static.surfconext.nl/logos/idp/ROCMNlogo.png",
        "coin:institution_guid": "e7adb9d1-0911-e511-80d0-005056956c1a"
      }
    }
  },
  {
    "_id": "ff99e7aa-7c8e-47f0-855f-d6976380e62e",
    "version": 38,
    "type": "saml20_idp",
    "data": {
      "entityid": "https://shibtestidp.pt-27.utr.surfcloud.nl/idp/shibboleth",
      "state": "prodaccepted",
      "notes": null,
      "metaDataFields": {
        "name:nl": "EncAssertion Shib IdP",
        "name:en": "EncAssertion Shib IdP",
        "coin:institution_brin_schac_home": "surfcloud.nl",
        "shibmd:scope:0:allowed": "surfcloud.nl",
        "shibmd:scope:1:allowed": "nope.mope",
        "coin:institution_guid": "noppy"
      }
    }
  },
  {
    "_id": "f660b318-06ed-4ff4-b044-9fee5527475f",
    "version": 7,
    "type": "saml20_idp",
    "data": {
      "entityid": "https://beta.surfnet.nl/SURFdropjesIdP2",
      "state": "prodaccepted",
      "metaDataFields": {
        "name:en": "SURFdrops Beta IdP",
        "OrganizationName:en": "SURFdropjes Beta",
        "OrganizationName:nl": "SURFdropjes Beta",
        "logo:0:url": "https://static.surfconext.nl/media/sp/SURFdropsBeta.png",
        "coin:institution_brin_schac_home": "braindrops.nl",
        "shibmd:scope:0:allowed": "braindrops.nl",
        "shibmd:scope:1:allowed": "groningen.nl",
        "shibmd:scope:2:allowed": "surfnet.nl",
        "shibmd:scope:3:allowed": "dropjes.surfnet.nl",
        "name:nl": "SURFdrops Beta IdP",
        "coin:institution_guid": "409542a0-0d11-e511-80d0-005056956c1a"
      }
    }
  }
]